[{"StrikeRes": -2, "FireRes": 1, "dhsid": [37, 38], "MAT": 8, "ElecDmg": 2, "ATKFactor": 0.2, "equipKinds": [21, 22, 23, 41, 62, 72, 101], "MATFactor": 1.2, "desid": [37, 38], "HolyDmg": 2, "DarkDmg": 2, "FireDmg": 2, "ElecRes": 1, "SlashRes": -2, "IceRes": 1, "DarkRes": 1, "STR": 1, "HP": 80, "INT": 10, "SPD": 250.0, "MPREC": 0.01, "name": "Elementalist", "HolyRes": 1, "IceDmg": 2, "MP": 100, "type": 1, "WindRes": 1, "res": "Elementalist", "id": "D8F7FD5D", "DEFFactor": 0.5, "MPRECFactor": 0.001, "WindDmg": 2, "MPFactor": 1.0, "MDF": 5, "HPFactor": 0.5, "CON": 1, "dwid": 1, "MDFFactor": 1.0, "ATK": 1, "DEF": 1, "MEN": 8}, {"dhsid": [43, 44], "MAT": 1, "ATKFactor": 0.7, "equipKinds": [1, 2, 3, 4, 5, 21, 43, 44, 61, 71, 102], "MATFactor": 0.1, "desid": [43, 44], "STR": 7, "HP": 95, "INT": 1, "SPD": 260.0, "MPREC": 0.01, "name": "Gerald", "MP": 60, "type": 1, "res": "Gerald", "id": "F9F92BA0", "DEFFactor": 0.8, "MPRECFactor": 0.001, "MPFactor": 0.4, "MDF": 1, "HPFactor": 0.8, "CON": 5, "dwid": 42, "MDFFactor": 0.1, "ATK": 6, "DEF": 4, "MEN": 1}, {"res": "Battery", "name": "Battery", "ATK": 10}, {"res": "CircularSaw", "name": "CircularSaw", "ATK": 20, "SlashDmg": 3}, {"SPD": 0.0, "name": "EvilCat", "DarkRes": 3, "MDF": 2, "res": "EvilCat", "HolyRes": -3, "ATK": 10, "DEF": 5, "HP": 50}, {"res": "FlameThrower", "name": "FlameThrower", "FireDmg": 5, "ATK": 16}, {"SPD": 200.0, "name": "Gargoyle", "MDF": 8, "res": "Gargoyle", "ATK": 15, "DEF": 5, "HP": 60}, {"StrikeRes": 2, "name": "HighSkullGhost", "FireRes": -2, "SlashRes": 2, "DarkRes": 3, "HolyRes": -5, "res": "HighSkullGhost", "HP": 25, "DarkDmg": 2, "ATK": 12, "SPD": 90.0}, {"SPD": 300.0, "name": "HornBeast", "DarkRes": 4, "ElecRes": 6, "MDF": 21, "MAT": 28, "res": "HornBeast", "HolyRes": -4, "ATK": 22, "DEF": 19, "HP": 900}, {"SPD": 80.0, "name": "LanceWarrior", "ElecRes": -4, "MDF": 8, "StrikeRes": -4, "SlashRes": 4, "res": "LanceWarrior", "ATK": 20, "DEF": 15, "HP": 120}, {"SPD": 0.0, "name": "LionPillar", "FireDmg": 2, "MDF": 10, "StrikeRes": -2, "res": "LionPillar", "ATK": 5, "DEF": 10, "HP": 90}, {"SPD": 140.0, "name": "LizardAxeman", "FireRes": -2, "ElecRes": -3, "MDF": 5, "IceRes": 2, "res": "LizardAxeman", "ATK": 12, "DEF": 8, "HP": 80}, {"StrikeRes": 2, "name": "Rhinoceros", "MAT": 10, "res": "Rhinoceros", "ATK": 15, "FireDmg": 3, "DEF": 18, "SlashRes": 2, "IceRes": -2, "HP": 150, "SPD": 0.0, "MDF": 16}, {"res": "RotatingBlade", "name": "RotatingBlade", "ATK": 20}, {"res": "Sickle", "name": "Sickle", "ATK": 20, "SlashDmg": 3}, {"StrikeRes": -1, "name": "Skeleton", "FireRes": -2, "res": "Skeleton", "ATK": 10, "DarkRes": 3, "DEF": 4, "SlashRes": 2, "HP": 50, "HolyRes": -4, "SPD": 140.0, "MDF": 1}, {"SPD": 130.0, "name": "SkeletonArcher", "FireRes": -2, "MDF": 1, "StrikeRes": -2, "DarkRes": 3, "res": "SkeletonArcher", "HolyRes": -4, "ATK": 15, "DEF": 2, "HP": 40}, {"StrikeRes": -3, "name": "SkeletonMage", "FireRes": 2, "MAT": 15, "ElecDmg": 2, "WindRes": 3, "res": "SkeletonMage", "HolyRes": -2, "ATK": 5, "DarkRes": 4, "ElecRes": 5, "DEF": 1, "IceRes": 3, "HP": 35, "SPD": 120.0, "MDF": 5}, {"SPD": 50.0, "name": "Slime", "FireRes": -4, "MDF": 3, "StrikeRes": 4, "SlashRes": 3, "res": "Slime", "ATK": 5, "DEF": 3, "HP": 25}, {"res": "SpikeTrap", "name": "SpikeTrap", "ATK": 20}, {"res": "StaticSpike", "name": "StaticSpike", "ATK": 20}, {"StrikeRes": 2, "name": "SkullGhost", "HolyRes": -2, "SlashRes": 2, "DarkRes": 2, "res": "SkullGhost", "HP": 15, "ATK": 10, "SPD": 70.0}, {"SPD": 70.0, "name": "Zombie", "FireRes": -4, "MDF": 2, "DarkRes": 2, "res": "Zombie", "HolyRes": -5, "ATK": 10, "DEF": 3, "HP": 45}]